myc/__init__.py
myc/app.py
myc/awslambda.py
myc/build.py
myc/common.py
myc/endpoint.py
myc/fastapi_.py
myc/invoke.py
myc/ledger.py
myc/schema.py
myc/serialization.py
myc/service.py
myc-0.1.2.dist-info/LICENSE
myc-0.1.2.dist-info/WHEEL
myc-0.1.2.dist-info/METADATA
myc-0.1.2.dist-info/RECORD
