Metadata-Version: 2.1
Name: myc
Version: 0.1.2
Summary: 
Home-page: https://github.com/BizarreCake/myc
License: MIT
Author: Jacob Zhitomirsky
Author-email: bizarrecake@gmail.com
Requires-Python: >=3.9,<4.0
Classifier: License :: OSI Approved :: MIT License
Classifier: Programming Language :: Python :: 3
Classifier: Programming Language :: Python :: 3.9
Classifier: Programming Language :: Python :: 3.10
Requires-Dist: boto3 (>=1.24.80,<2.0.0)
Requires-Dist: dnspython (>=2.2.1,<3.0.0)
Requires-Dist: fastapi (>=0.85.0,<0.86.0)
Requires-Dist: magnum (>=15.0.0,<16.0.0)
Requires-Dist: requests (>=2.28.1,<3.0.0)
Project-URL: Repository, https://github.com/BizarreCake/myc
